racetime_bot/__init__.py
racetime_bot/bot.py
racetime_bot/handler.py
racetime_bot/msg_actions.py
racetime_bot-2.3.0.dist-info/licenses/LICENSE
racetime_bot-2.3.0.dist-info/METADATA
racetime_bot-2.3.0.dist-info/WHEEL
racetime_bot-2.3.0.dist-info/top_level.txt
racetime_bot-2.3.0.dist-info/RECORD
