Metadata-Version: 2.4
Name: racetime-bot
Version: 2.3.0
Summary: Foundation system for creating chat bots for racetime.gg
Home-page: https://github.com/racetimeGG/racetime-bot
License: MIT
Project-URL: Source, https://github.com/racetimeGG/racetime-bot
Classifier: Development Status :: 5 - Production/Stable
Classifier: Intended Audience :: Developers
Classifier: License :: OSI Approved :: MIT License
Classifier: Programming Language :: Python :: 3.7
Classifier: Programming Language :: Python :: 3.8
Classifier: Programming Language :: Python :: 3.9
License-File: LICENSE
Requires-Dist: aiohttp
Requires-Dist: asgiref
Requires-Dist: requests
Requires-Dist: websockets
Dynamic: classifier
Dynamic: home-page
Dynamic: license
Dynamic: license-file
Dynamic: project-url
Dynamic: requires-dist
Dynamic: summary
